README.md
setup.py
doudizhu/__init__.py
doudizhu/card.py
doudizhu/compat.py
doudizhu/engine.py
doudizhu.egg-info/PKG-INFO
doudizhu.egg-info/SOURCES.txt
doudizhu.egg-info/dependency_links.txt
doudizhu.egg-info/top_level.txt