Metadata-Version: 1.1
Name: doudizhu
Version: 0.1.5
Summary: doudizhu engine
Home-page: https://github.com/onestraw/doudizhu
Author: onestraw
Author-email: hexiaowei91@gmail.com
License: MIT License
